{"rows":13,"cols":13,"words":["GEARSHIFT","INSURANCE","INDICATOR","KILOMETER","SPEEDING","EMISSION","OVERPASS","DRIVEWAY","PAVEMENT","TERRACE","FREEWAY","WARNING","CIRCLE","GUTTER","TRUCK","ALLEY","FAST","ROAD","SIGN","TURN"],"boardCharacters":[["S","D","T","T","B","P","E","G","W","P","N","E","H"],["H","A","F","T","W","A","M","U","O","H","R","C","K"],["I","O","I","E","W","V","I","T","C","J","U","N","I"],["E","R","H","C","Q","E","S","T","Y","A","T","A","L"],["Z","I","S","A","F","M","S","E","E","F","O","R","O"],["S","N","R","R","R","E","I","R","L","L","A","U","M"],["S","D","A","R","E","N","O","T","L","Y","F","S","E"],["A","I","E","E","E","T","N","C","A","F","B","N","T"],["P","C","G","T","W","T","R","U","C","K","K","I","E"],["R","A","P","N","A","C","I","R","C","L","E","K","R"],["E","T","M","D","Y","Y","A","W","E","V","I","R","D"],["V","O","U","V","B","M","W","A","R","N","I","N","G"],["O","R","J","I","S","G","N","I","D","E","E","P","S"]],"wordPlacements":[{"word":"GEARSHIFT","row":8,"col":2,"h":0,"v":-1},{"word":"INSURANCE","row":8,"col":11,"h":0,"v":-1},{"word":"INDICATOR","row":4,"col":1,"h":0,"v":1},{"word":"KILOMETER","row":1,"col":12,"h":0,"v":1},{"word":"SPEEDING","row":12,"col":12,"h":-1,"v":0},{"word":"EMISSION","row":0,"col":6,"h":0,"v":1},{"word":"OVERPASS","row":12,"col":0,"h":0,"v":-1},{"word":"DRIVEWAY","row":10,"col":12,"h":-1,"v":0},{"word":"PAVEMENT","row":0,"col":5,"h":0,"v":1},{"word":"TERRACE","row":8,"col":3,"h":0,"v":-1},{"word":"FREEWAY","row":4,"col":4,"h":0,"v":1},{"word":"WARNING","row":11,"col":6,"h":1,"v":0},{"word":"CIRCLE","row":9,"col":5,"h":1,"v":0},{"word":"GUTTER","row":0,"col":7,"h":0,"v":1},{"word":"TRUCK","row":8,"col":5,"h":1,"v":0},{"word":"ALLEY","row":7,"col":8,"h":0,"v":-1},{"word":"FAST","row":4,"col":9,"h":1,"v":1},{"word":"ROAD","row":3,"col":1,"h":0,"v":-1},{"word":"SIGN","row":6,"col":0,"h":1,"v":1},{"word":"TURN","row":3,"col":10,"h":0,"v":-1}]}