{"rows":10,"cols":10,"words":["GRIDLOCK","BARRIER","EXHAUST","BICYCLE","ASPHALT","LIGHTS","AVENUE","DANGER","SAFETY","TRUCK","MERGE","TOLL","ROAD","TURN","GAS","MAP"],"boardCharacters":[["E","E","F","U","K","N","R","U","T","S"],["U","L","W","E","C","Y","Y","B","S","T"],["N","A","G","G","U","L","T","I","U","H"],["E","S","R","R","R","T","E","C","A","G"],["V","P","I","E","T","O","F","Y","H","I"],["A","H","D","M","C","L","A","C","X","L"],["D","A","L","A","T","L","S","L","E","Y"],["G","L","O","K","O","M","S","E","Z","J"],["A","T","C","B","A","R","R","I","E","R"],["S","D","K","P","R","E","G","N","A","D"]],"wordPlacements":[{"word":"GRIDLOCK","row":2,"col":2,"h":0,"v":1},{"word":"BARRIER","row":8,"col":3,"h":1,"v":0},{"word":"EXHAUST","row":6,"col":8,"h":0,"v":-1},{"word":"BICYCLE","row":1,"col":7,"h":0,"v":1},{"word":"ASPHALT","row":2,"col":1,"h":0,"v":1},{"word":"LIGHTS","row":5,"col":9,"h":0,"v":-1},{"word":"AVENUE","row":5,"col":0,"h":0,"v":-1},{"word":"DANGER","row":9,"col":9,"h":-1,"v":0},{"word":"SAFETY","row":6,"col":6,"h":0,"v":-1},{"word":"TRUCK","row":4,"col":4,"h":0,"v":-1},{"word":"MERGE","row":5,"col":3,"h":0,"v":-1},{"word":"TOLL","row":3,"col":5,"h":0,"v":1},{"word":"ROAD","row":8,"col":5,"h":-1,"v":-1},{"word":"TURN","row":0,"col":8,"h":-1,"v":0},{"word":"GAS","row":7,"col":0,"h":0,"v":1},{"word":"MAP","row":7,"col":5,"h":-1,"v":1}]}