{"rows":7,"cols":7,"words":["SAILOR","HOIST","DRIFT","SHIP","TIDE","ROPE","FURL","WAKE","AFT","BOW"],"boardCharacters":[["R","R","O","L","I","A","S"],["O","K","D","R","I","F","T"],["P","B","Z","U","L","M","E"],["E","O","Z","F","E","Y","D"],["T","W","W","A","K","E","I"],["L","F","H","O","I","S","T"],["N","N","A","S","H","I","P"]],"wordPlacements":[{"word":"SAILOR","row":0,"col":6,"h":-1,"v":0},{"word":"HOIST","row":5,"col":2,"h":1,"v":0},{"word":"DRIFT","row":1,"col":2,"h":1,"v":0},{"word":"SHIP","row":6,"col":3,"h":1,"v":0},{"word":"TIDE","row":5,"col":6,"h":0,"v":-1},{"word":"ROPE","row":0,"col":0,"h":0,"v":1},{"word":"FURL","row":3,"col":3,"h":0,"v":-1},{"word":"WAKE","row":4,"col":2,"h":1,"v":0},{"word":"AFT","row":6,"col":2,"h":-1,"v":-1},{"word":"BOW","row":2,"col":1,"h":0,"v":1}]}