{"rows":13,"cols":13,"words":["ADMISSION","AMUSEMENT","STAGEHAND","LEMONADE","JAMBOREE","SIDESHOW","FUNFAIR","APPLAUD","LEOTARD","ANIMALS","JUGGLER","TICKET","PARADE","MAGIC","GIANT","CLOWN","CANDY","FEAST","SEAL","CAPE","DOG"],"boardCharacters":[["F","U","N","F","A","I","R","T","S","A","E","F","T"],["D","R","E","L","G","G","U","J","Q","B","Q","T","N"],["D","U","A","L","P","P","A","E","D","T","N","I","E"],["H","B","C","L","O","W","N","P","N","S","O","C","M"],["W","D","J","L","E","O","T","A","R","D","I","K","E"],["O","E","A","F","V","U","I","C","W","P","S","E","S"],["H","A","M","Q","S","G","Z","W","G","A","S","T","U"],["S","N","B","C","I","G","A","M","F","R","I","W","M"],["E","I","O","Y","L","A","E","S","D","A","M","N","A"],["D","M","R","D","W","B","Q","W","L","D","D","O","G"],["I","A","E","N","K","I","V","K","I","E","A","A","Q"],["S","L","E","A","D","N","A","H","E","G","A","T","S"],["V","S","Q","C","L","L","E","M","O","N","A","D","E"]],"wordPlacements":[{"word":"ADMISSION","row":10,"col":10,"h":0,"v":-1},{"word":"AMUSEMENT","row":8,"col":12,"h":0,"v":-1},{"word":"STAGEHAND","row":11,"col":12,"h":-1,"v":0},{"word":"LEMONADE","row":12,"col":5,"h":1,"v":0},{"word":"JAMBOREE","row":4,"col":2,"h":0,"v":1},{"word":"SIDESHOW","row":11,"col":0,"h":0,"v":-1},{"word":"FUNFAIR","row":0,"col":0,"h":1,"v":0},{"word":"APPLAUD","row":2,"col":6,"h":-1,"v":0},{"word":"LEOTARD","row":4,"col":3,"h":1,"v":0},{"word":"ANIMALS","row":6,"col":1,"h":0,"v":1},{"word":"JUGGLER","row":1,"col":7,"h":-1,"v":0},{"word":"TICKET","row":1,"col":11,"h":0,"v":1},{"word":"PARADE","row":5,"col":9,"h":0,"v":1},{"word":"MAGIC","row":7,"col":7,"h":-1,"v":0},{"word":"GIANT","row":6,"col":5,"h":1,"v":-1},{"word":"CLOWN","row":3,"col":2,"h":1,"v":0},{"word":"CANDY","row":12,"col":3,"h":0,"v":-1},{"word":"FEAST","row":0,"col":11,"h":-1,"v":0},{"word":"SEAL","row":8,"col":7,"h":-1,"v":0},{"word":"CAPE","row":5,"col":7,"h":0,"v":-1},{"word":"DOG","row":9,"col":10,"h":1,"v":0}]}