{"rows":10,"cols":10,"words":["COMPOUND","AQUEDUCT","PYRAMID","COLLEGE","COTTAGE","FOUNDRY","SKYWAY","PALACE","CEMENT","CHALET","VILLA","TIPI","FARM","SHED","HUT"],"boardCharacters":[["T","P","V","B","S","H","E","D","F","M"],["C","X","W","I","P","I","T","A","O","C"],["U","U","E","W","K","Y","R","X","U","E"],["D","P","Y","R","A","M","I","D","N","M"],["E","Y","A","W","Y","K","S","Y","D","E"],["U","C","H","A","L","E","T","U","R","N"],["Q","V","A","V","I","L","L","A","Y","T"],["A","C","O","L","L","E","G","E","U","B"],["C","O","T","T","A","G","E","H","J","C"],["X","D","N","U","O","P","M","O","C","D"]],"wordPlacements":[{"word":"COMPOUND","row":9,"col":8,"h":-1,"v":0},{"word":"AQUEDUCT","row":7,"col":0,"h":0,"v":-1},{"word":"PYRAMID","row":3,"col":1,"h":1,"v":0},{"word":"COLLEGE","row":7,"col":1,"h":1,"v":0},{"word":"COTTAGE","row":8,"col":0,"h":1,"v":0},{"word":"FOUNDRY","row":0,"col":8,"h":0,"v":1},{"word":"SKYWAY","row":4,"col":6,"h":-1,"v":0},{"word":"PALACE","row":9,"col":5,"h":-1,"v":-1},{"word":"CEMENT","row":1,"col":9,"h":0,"v":1},{"word":"CHALET","row":5,"col":1,"h":1,"v":0},{"word":"VILLA","row":6,"col":3,"h":1,"v":0},{"word":"TIPI","row":1,"col":6,"h":-1,"v":0},{"word":"FARM","row":0,"col":8,"h":-1,"v":1},{"word":"SHED","row":0,"col":4,"h":1,"v":0},{"word":"HUT","row":8,"col":7,"h":1,"v":-1}]}