{"rows":7,"cols":7,"words":["HUMVEE","BARROW","SUBWAY","VESSEL","MOTOR","PLANE","WRECK","VESPA","WAGON"],"boardCharacters":[["S","U","B","W","A","Y","W"],["V","E","S","S","E","L","A"],["V","K","C","E","R","W","G"],["E","E","V","M","U","H","O"],["S","P","L","A","N","E","N"],["P","B","A","R","R","O","W"],["A","Y","M","O","T","O","R"]],"wordPlacements":[{"word":"HUMVEE","row":3,"col":5,"h":-1,"v":0},{"word":"BARROW","row":5,"col":1,"h":1,"v":0},{"word":"SUBWAY","row":0,"col":0,"h":1,"v":0},{"word":"VESSEL","row":1,"col":0,"h":1,"v":0},{"word":"MOTOR","row":6,"col":2,"h":1,"v":0},{"word":"PLANE","row":4,"col":1,"h":1,"v":0},{"word":"WRECK","row":2,"col":5,"h":-1,"v":0},{"word":"VESPA","row":2,"col":0,"h":0,"v":1},{"word":"WAGON","row":0,"col":6,"h":0,"v":1}]}