{"rows":13,"cols":13,"words":["SPACESHIP","HOUSEBOAT","DIRIGIBLE","RIVERBOAT","GRIDLOCK","FIREBOAT","MONORAIL","RAILWAY","TRAILER","GLIDER","RUDDER","CONVOY","SLEDGE","PADDLE","JALOPY","LORRY","MOPED","CYCLE","HULL","BIKE","OAR"],"boardCharacters":[["T","R","C","N","D","E","P","O","M","I","D","I","E"],["T","R","S","L","E","D","G","E","N","R","L","R","P"],["S","P","A","C","E","S","H","I","P","U","I","I","T"],["D","I","R","I","G","I","B","L","E","D","A","V","S"],["T","J","C","B","L","L","B","Z","I","D","R","E","G"],["M","H","L","F","I","E","G","A","L","E","O","R","K"],["P","C","K","C","D","K","R","R","L","R","N","B","C"],["A","O","J","U","E","P","E","B","U","G","O","O","O"],["D","N","A","Q","R","Z","F","Y","H","E","M","A","L"],["D","V","L","C","Y","C","L","E","R","L","R","T","D"],["L","O","O","Y","T","A","O","B","E","R","I","F","I"],["E","Y","P","T","A","O","B","E","S","U","O","H","R"],["R","N","Y","X","R","A","I","L","W","A","Y","L","G"]],"wordPlacements":[{"word":"SPACESHIP","row":2,"col":0,"h":1,"v":0},{"word":"HOUSEBOAT","row":11,"col":11,"h":-1,"v":0},{"word":"DIRIGIBLE","row":3,"col":0,"h":1,"v":0},{"word":"RIVERBOAT","row":1,"col":11,"h":0,"v":1},{"word":"GRIDLOCK","row":12,"col":12,"h":0,"v":-1},{"word":"FIREBOAT","row":10,"col":11,"h":-1,"v":0},{"word":"MONORAIL","row":8,"col":10,"h":0,"v":-1},{"word":"RAILWAY","row":12,"col":4,"h":1,"v":0},{"word":"TRAILER","row":0,"col":0,"h":1,"v":1},{"word":"GLIDER","row":3,"col":4,"h":0,"v":1},{"word":"RUDDER","row":1,"col":9,"h":0,"v":1},{"word":"CONVOY","row":6,"col":1,"h":0,"v":1},{"word":"SLEDGE","row":1,"col":2,"h":1,"v":0},{"word":"PADDLE","row":6,"col":0,"h":0,"v":1},{"word":"JALOPY","row":7,"col":2,"h":0,"v":1},{"word":"LORRY","row":12,"col":11,"h":-1,"v":-1},{"word":"MOPED","row":0,"col":8,"h":-1,"v":0},{"word":"CYCLE","row":9,"col":3,"h":1,"v":0},{"word":"HULL","row":8,"col":8,"h":0,"v":-1},{"word":"BIKE","row":4,"col":3,"h":1,"v":1},{"word":"OAR","row":7,"col":12,"h":-1,"v":1}]}