{"rows":7,"cols":7,"words":["CREATE","ERASER","ARTIST","MUSEUM","CARVE","ERASE","FRAME","EASEL","FORM","LINE"],"boardCharacters":[["T","S","I","T","R","A","F"],["C","R","E","A","T","E","R"],["A","F","O","R","M","E","A"],["R","M","U","E","S","U","M"],["V","E","S","A","R","E","E"],["E","I","R","L","I","N","E"],["U","E","E","A","S","E","L"]],"wordPlacements":[{"word":"CREATE","row":1,"col":0,"h":1,"v":0},{"word":"ERASER","row":6,"col":1,"h":1,"v":-1},{"word":"ARTIST","row":0,"col":5,"h":-1,"v":0},{"word":"MUSEUM","row":3,"col":6,"h":-1,"v":0},{"word":"CARVE","row":1,"col":0,"h":0,"v":1},{"word":"ERASE","row":4,"col":5,"h":-1,"v":0},{"word":"FRAME","row":0,"col":6,"h":0,"v":1},{"word":"EASEL","row":6,"col":2,"h":1,"v":0},{"word":"FORM","row":2,"col":1,"h":1,"v":0},{"word":"LINE","row":5,"col":3,"h":1,"v":0}]}