{"rows":10,"cols":10,"words":["BOBWHITE","COCKATOO","WARBLER","FEATHER","COWBIRD","ROOSTER","TANAGER","PEACOCK","CONDOR","EIDER","EGRET","MACAW","BEAK","NENE","CROW"],"boardCharacters":[["E","T","I","H","W","B","O","B","R","K"],["C","O","C","K","A","T","O","O","O","L"],["R","P","E","A","C","O","C","K","O","D"],["R","E","H","T","A","E","F","G","S","R"],["E","N","D","C","M","G","N","J","T","I"],["G","W","E","I","V","R","K","A","E","B"],["A","G","S","N","E","E","N","W","R","W"],["N","Y","F","W","E","T","O","R","W","O"],["A","R","E","L","B","R","A","W","L","C"],["T","T","T","Y","C","O","N","D","O","R"]],"wordPlacements":[{"word":"BOBWHITE","row":0,"col":7,"h":-1,"v":0},{"word":"COCKATOO","row":1,"col":0,"h":1,"v":0},{"word":"WARBLER","row":8,"col":7,"h":-1,"v":0},{"word":"FEATHER","row":3,"col":6,"h":-1,"v":0},{"word":"COWBIRD","row":8,"col":9,"h":0,"v":-1},{"word":"ROOSTER","row":0,"col":8,"h":0,"v":1},{"word":"TANAGER","row":9,"col":0,"h":0,"v":-1},{"word":"PEACOCK","row":2,"col":1,"h":1,"v":0},{"word":"CONDOR","row":9,"col":4,"h":1,"v":0},{"word":"EIDER","row":6,"col":4,"h":-1,"v":-1},{"word":"EGRET","row":3,"col":5,"h":0,"v":1},{"word":"MACAW","row":4,"col":4,"h":0,"v":-1},{"word":"BEAK","row":5,"col":9,"h":-1,"v":0},{"word":"NENE","row":4,"col":1,"h":1,"v":1},{"word":"CROW","row":9,"col":4,"h":1,"v":-1}]}