{"rows":10,"cols":10,"words":["PALMETTO","BUCKEYE","SEQUOIA","APRICOT","JUNGLE","CHERRY","BIRCH","LILAC","APPLE","BEECH","ASPEN","TREE","TEAK","IPIL","DATE","GUM"],"boardCharacters":[["H","E","T","O","C","I","R","P","A","I"],["C","Y","R","R","E","H","C","O","C","T"],["E","E","A","P","P","L","E","A","R","E"],["E","K","G","D","R","L","S","E","A","L"],["B","C","U","E","I","P","E","H","I","G"],["H","U","M","L","E","K","Q","P","O","N"],["V","B","A","N","M","A","I","X","U","U"],["H","C","R","I","B","E","I","D","Q","J"],["P","A","L","M","E","T","T","O","E","S"],["U","N","B","D","A","T","E","T","S","C"]],"wordPlacements":[{"word":"PALMETTO","row":8,"col":0,"h":1,"v":0},{"word":"BUCKEYE","row":6,"col":1,"h":0,"v":-1},{"word":"SEQUOIA","row":9,"col":8,"h":0,"v":-1},{"word":"APRICOT","row":0,"col":8,"h":-1,"v":0},{"word":"JUNGLE","row":7,"col":9,"h":0,"v":-1},{"word":"CHERRY","row":1,"col":6,"h":-1,"v":0},{"word":"BIRCH","row":7,"col":4,"h":-1,"v":0},{"word":"LILAC","row":3,"col":5,"h":-1,"v":1},{"word":"APPLE","row":2,"col":2,"h":1,"v":0},{"word":"BEECH","row":4,"col":0,"h":0,"v":-1},{"word":"ASPEN","row":2,"col":7,"h":-1,"v":1},{"word":"TREE","row":1,"col":9,"h":-1,"v":1},{"word":"TEAK","row":8,"col":5,"h":0,"v":-1},{"word":"IPIL","row":6,"col":6,"h":1,"v":-1},{"word":"DATE","row":9,"col":3,"h":1,"v":0},{"word":"GUM","row":3,"col":2,"h":0,"v":1}]}