{"rows":7,"cols":7,"words":["BUDGET","SELLER","MARKET","MARGIN","BONDS","SPEND","VALUE","EARN","BANK"],"boardCharacters":[["M","B","E","K","B","S","N"],["A","O","A","B","U","E","I"],["R","N","R","A","D","L","G"],["K","D","N","N","G","L","R"],["E","S","E","K","E","E","A"],["T","P","I","O","T","R","M"],["S","J","E","U","L","A","V"]],"wordPlacements":[{"word":"BUDGET","row":0,"col":4,"h":0,"v":1},{"word":"SELLER","row":0,"col":5,"h":0,"v":1},{"word":"MARKET","row":0,"col":0,"h":0,"v":1},{"word":"MARGIN","row":5,"col":6,"h":0,"v":-1},{"word":"BONDS","row":0,"col":1,"h":0,"v":1},{"word":"SPEND","row":6,"col":0,"h":1,"v":-1},{"word":"VALUE","row":6,"col":6,"h":-1,"v":0},{"word":"EARN","row":0,"col":2,"h":0,"v":1},{"word":"BANK","row":1,"col":3,"h":0,"v":1}]}