{"rows":10,"cols":10,"words":["ORDNANCE","HOWITZER","CARBINE","HARPOON","BAZOOKA","MAGNUM","KNOUT","LANCE","BOMB","KRIS","FOIL","MINE","EPEE","CLUB","GUN","UZI"],"boardCharacters":[["R","N","O","O","P","R","A","H","C","M"],["E","C","N","A","N","D","R","O","A","K"],["R","L","A","N","C","E","J","G","L","V"],["E","E","P","E","B","T","N","I","A","B"],["Z","E","H","U","U","U","O","N","M","A"],["T","M","L","O","M","F","Z","O","L","Z"],["I","C","N","G","P","D","B","I","W","O"],["W","K","G","G","K","R","I","S","Q","O"],["O","H","U","O","E","N","I","M","E","K"],["H","E","N","I","B","R","A","C","E","A"]],"wordPlacements":[{"word":"ORDNANCE","row":1,"col":7,"h":-1,"v":0},{"word":"HOWITZER","row":9,"col":0,"h":0,"v":-1},{"word":"CARBINE","row":9,"col":7,"h":-1,"v":0},{"word":"HARPOON","row":0,"col":7,"h":-1,"v":0},{"word":"BAZOOKA","row":3,"col":9,"h":0,"v":1},{"word":"MAGNUM","row":0,"col":9,"h":-1,"v":1},{"word":"KNOUT","row":7,"col":1,"h":1,"v":-1},{"word":"LANCE","row":2,"col":1,"h":1,"v":0},{"word":"BOMB","row":6,"col":6,"h":1,"v":-1},{"word":"KRIS","row":7,"col":4,"h":1,"v":0},{"word":"FOIL","row":5,"col":5,"h":1,"v":-1},{"word":"MINE","row":8,"col":7,"h":-1,"v":0},{"word":"EPEE","row":3,"col":3,"h":-1,"v":0},{"word":"CLUB","row":6,"col":1,"h":1,"v":-1},{"word":"GUN","row":7,"col":2,"h":0,"v":1},{"word":"UZI","row":4,"col":5,"h":1,"v":1}]}