{"rows":7,"cols":7,"words":["LIZARD","POODLE","PYTHON","SLOTH","ZORRO","QUOLL","ANOLE","KIWI","HARE"],"boardCharacters":[["Q","U","O","L","L","Z","H"],["R","E","O","D","P","O","T"],["I","L","R","R","Y","E","O"],["W","D","R","A","T","L","L"],["I","O","O","Z","H","O","S"],["K","O","Z","I","O","N","F"],["O","P","D","L","N","A","T"]],"wordPlacements":[{"word":"LIZARD","row":6,"col":3,"h":0,"v":-1},{"word":"POODLE","row":6,"col":1,"h":0,"v":-1},{"word":"PYTHON","row":1,"col":4,"h":0,"v":1},{"word":"SLOTH","row":4,"col":6,"h":0,"v":-1},{"word":"ZORRO","row":5,"col":2,"h":0,"v":-1},{"word":"QUOLL","row":0,"col":0,"h":1,"v":0},{"word":"ANOLE","row":6,"col":5,"h":0,"v":-1},{"word":"KIWI","row":5,"col":0,"h":0,"v":-1},{"word":"HARE","row":4,"col":4,"h":-1,"v":-1}]}