{"rows":10,"cols":10,"words":["DIGITAL","UTILITY","SPAMMER","ENCRYPT","ADDRESS","NETWORK","SERVER","FLASH","PRINT","TABLE","HELP","WIKI","PAGE","FONT","WEB"],"boardCharacters":[["S","B","F","U","T","I","L","I","T","Y"],["P","F","O","D","I","G","I","T","A","L"],["A","L","N","W","P","L","E","H","D","K"],["M","A","T","N","E","X","W","X","D","R"],["M","S","H","T","W","B","Y","O","R","O"],["E","H","T","P","Y","R","C","N","E","W"],["R","E","V","R","E","S","W","U","S","T"],["B","T","H","E","L","B","A","T","S","E"],["V","W","I","K","I","E","G","A","P","N"],["S","R","P","R","I","N","T","U","Z","M"]],"wordPlacements":[{"word":"DIGITAL","row":1,"col":3,"h":1,"v":0},{"word":"UTILITY","row":0,"col":3,"h":1,"v":0},{"word":"SPAMMER","row":0,"col":0,"h":0,"v":1},{"word":"ENCRYPT","row":5,"col":8,"h":-1,"v":0},{"word":"ADDRESS","row":1,"col":8,"h":0,"v":1},{"word":"NETWORK","row":8,"col":9,"h":0,"v":-1},{"word":"SERVER","row":6,"col":5,"h":-1,"v":0},{"word":"FLASH","row":1,"col":1,"h":0,"v":1},{"word":"PRINT","row":9,"col":2,"h":1,"v":0},{"word":"TABLE","row":7,"col":7,"h":-1,"v":0},{"word":"HELP","row":2,"col":7,"h":-1,"v":0},{"word":"WIKI","row":8,"col":1,"h":1,"v":0},{"word":"PAGE","row":8,"col":8,"h":-1,"v":0},{"word":"FONT","row":0,"col":2,"h":0,"v":1},{"word":"WEB","row":2,"col":3,"h":1,"v":1}]}