{"rows":7,"cols":7,"words":["GRAMPA","GRAMPS","ORPHAN","MINOR","NIECE","GROOM","BRIDE","KITH","POP","WED"],"boardCharacters":[["E","I","R","G","D","G","N"],["E","O","O","R","E","R","N"],["D","H","N","A","W","A","N"],["I","T","I","M","H","M","I"],["R","I","M","P","O","P","E"],["B","K","R","A","Y","S","C"],["M","O","O","R","G","B","E"]],"wordPlacements":[{"word":"GRAMPA","row":0,"col":3,"h":0,"v":1},{"word":"GRAMPS","row":0,"col":5,"h":0,"v":1},{"word":"ORPHAN","row":6,"col":1,"h":1,"v":-1},{"word":"MINOR","row":4,"col":2,"h":0,"v":-1},{"word":"NIECE","row":2,"col":6,"h":0,"v":1},{"word":"GROOM","row":6,"col":4,"h":-1,"v":0},{"word":"BRIDE","row":5,"col":0,"h":0,"v":-1},{"word":"KITH","row":5,"col":1,"h":0,"v":-1},{"word":"POP","row":4,"col":3,"h":1,"v":0},{"word":"WED","row":2,"col":4,"h":0,"v":-1}]}