{"rows":7,"cols":6,"words":["BALL","BARREL","DICE","DOUGH","MARBLE","WHEEL"],"boardCharacters":[["M","c","B","w","y","H"],["A","W","q","A","G","u"],["R","m","H","U","L","D"],["B","n","O","e","I","L"],["L","D","r","C","E","c"],["E","l","E","k","d","L"],["B","A","R","R","E","L"]],"wordPlacements":[{"word":"BALL","row":0,"col":2,"h":1,"v":-1},{"word":"BARREL","row":6,"col":0,"h":1,"v":0},{"word":"DICE","row":2,"col":5,"h":-1,"v":-1},{"word":"DOUGH","row":4,"col":1,"h":1,"v":1},{"word":"MARBLE","row":0,"col":0,"h":0,"v":-1},{"word":"WHEEL","row":1,"col":1,"h":1,"v":-1}]}