{"rows":6,"cols":6,"words":["AQUA","DROP","FLOOD","LAKE","MOIST","TIDE","WELL"],"boardCharacters":[["w","F","L","O","O","D"],["p","T","A","M","a","L"],["D","I","Q","O","E","L"],["R","D","U","I","K","E"],["O","E","A","S","A","W"],["P","u","o","T","L","m"]],"wordPlacements":[{"word":"AQUA","row":1,"col":2,"h":0,"v":-1},{"word":"DROP","row":2,"col":0,"h":0,"v":-1},{"word":"FLOOD","row":0,"col":1,"h":1,"v":0},{"word":"LAKE","row":5,"col":4,"h":0,"v":1},{"word":"MOIST","row":1,"col":3,"h":0,"v":-1},{"word":"TIDE","row":1,"col":1,"h":0,"v":-1},{"word":"WELL","row":4,"col":5,"h":0,"v":1}]}