{"rows":7,"cols":7,"words":["SQUASH","UMPIRE","BATTER","SLALOM","WALKER","PITCH","CUE","RUN","BAT","OUT"],"boardCharacters":[["W","A","L","K","E","R","A"],["R","H","C","T","I","P","U"],["E","M","O","L","A","L","S"],["T","U","M","P","I","R","E"],["T","G","G","T","R","U","N"],["A","S","Q","U","A","S","H"],["B","H","E","U","C","B","E"]],"wordPlacements":[{"word":"SQUASH","row":5,"col":1,"h":1,"v":0},{"word":"UMPIRE","row":3,"col":1,"h":1,"v":0},{"word":"BATTER","row":6,"col":0,"h":0,"v":-1},{"word":"SLALOM","row":2,"col":6,"h":-1,"v":0},{"word":"WALKER","row":0,"col":0,"h":1,"v":0},{"word":"PITCH","row":1,"col":5,"h":-1,"v":0},{"word":"CUE","row":6,"col":4,"h":-1,"v":0},{"word":"RUN","row":4,"col":4,"h":1,"v":0},{"word":"BAT","row":6,"col":5,"h":-1,"v":-1},{"word":"OUT","row":2,"col":2,"h":-1,"v":1}]}